{
  "examples": {
    "dynamic_routing": {
      "example": "dynamic_routing",
      "metadata": {
        "best_optimization": "optimized_dynamic_routing",
        "best_optimization_file": "optimized_dynamic_routing.py",
        "best_optimization_speedup": 16.210530934968126,
        "best_optimization_time_ms": 0.12929200194776058,
        "git_commit": "2e62787eff329e2d792c1e48583eace9d4ddad8e",
        "updated_at": "2025-11-29T18:37:18.020923"
      },
      "metrics": {
        "baseline_p75_ms": 1.3923519849777222,
        "baseline_throughput.latency_ms": 1.4317120015621185,
        "baseline_throughput.requests_per_s": 715227.6427680494,
        "baseline_throughput.tokens_per_s": 91549138.27431032,
        "baseline_time_ms": 1.4317120015621185,
        "best_optimized_p75_ms": 0.0783040001988411,
        "best_optimized_speedup": 16.210530934968126,
        "best_optimized_throughput.latency_ms": 0.12929200194776058,
        "best_optimized_throughput.requests_per_s": 7920056.806094929,
        "best_optimized_throughput.tokens_per_s": 1013767271.1801509,
        "best_optimized_time_ms": 0.12929200194776058,
        "best_speedup": 16.210530934968126
      },
      "type": "python"
    },
    "inference_full": {
      "example": "inference_full",
      "metadata": {
        "best_optimization": "optimized_inference_full",
        "best_optimization_file": "optimized_inference_full.py",
        "best_optimization_speedup": 2.475830155582422,
        "best_optimization_time_ms": 0.39717567801475523,
        "git_commit": "2e62787eff329e2d792c1e48583eace9d4ddad8e",
        "updated_at": "2025-11-29T18:37:22.865749"
      },
      "metrics": {
        "baseline_p75_ms": 0.9698560237884521,
        "baseline_throughput.latency_ms": 0.9833395206928253,
        "baseline_throughput.requests_per_s": 16271.08405927485,
        "baseline_throughput.tokens_per_s": 33323180.153394893,
        "baseline_time_ms": 0.9833395206928253,
        "best_optimized_p75_ms": 0.3717760145664215,
        "best_optimized_speedup": 2.475830155582422,
        "best_optimized_throughput.latency_ms": 0.3785248023271561,
        "best_optimized_throughput.requests_per_s": 42269.356992283225,
        "best_optimized_throughput.tokens_per_s": 86567643.12019604,
        "best_optimized_time_ms": 0.3785248023271561,
        "best_speedup": 2.475830155582422
      },
      "type": "python"
    },
    "memory": {
      "example": "memory",
      "metadata": {
        "best_optimization": "optimized_memory",
        "best_optimization_file": "optimized_memory.py",
        "best_optimization_speedup": 21.442062070700736,
        "best_optimization_time_ms": 0.7978952002525329,
        "git_commit": "7c54dd7a5f2ab25b1d0153be8339fd5d1ee294f5",
        "updated_at": "2025-11-29T05:45:22.359962"
      },
      "metrics": {
        "baseline_p75_ms": 14.592384338378906,
        "baseline_throughput.latency_ms": 15.245405006408692,
        "baseline_throughput.requests_per_s": 524.7482763912832,
        "baseline_throughput.tokens_per_s": 550238448.6652662,
        "baseline_time_ms": 15.245405006408692,
        "best_optimized_p75_ms": 0.8133440017700195,
        "best_optimized_speedup": 21.442062070700736,
        "best_optimized_throughput.latency_ms": 0.8128492802381515,
        "best_optimized_throughput.requests_per_s": 9841.92296714113,
        "best_optimized_throughput.tokens_per_s": 10320004217.192978,
        "best_optimized_time_ms": 0.8128492802381515,
        "best_speedup": 21.442062070700736
      },
      "type": "python"
    },
    "pipeline_parallelism": {
      "example": "pipeline_parallelism",
      "metadata": {
        "best_optimization": "optimized_pipeline_parallelism",
        "best_optimization_file": "optimized_pipeline_parallelism.py",
        "best_optimization_speedup": 1.05,
        "best_optimization_time_ms": 0.879383996129036,
        "git_commit": "31bb5bdcfabc2dd956bb8ce8988785b9f6559ed8",
        "updated_at": "2025-11-25T02:46:14.774946"
      },
      "metrics": {
        "baseline_p75_ms": 0.2348479926586151,
        "baseline_throughput.latency_ms": 0.26345119923353194,
        "baseline_throughput.requests_per_s": 3795.7693983148906,
        "baseline_throughput.samples_per_s": 971716.965968612,
        "baseline_throughput.tokens_per_s": 995038173.1518587,
        "baseline_time_ms": 0.26345119923353194,
        "best_optimized_p75_ms": 0.8038399815559387,
        "best_optimized_speedup": 0.29958607433523793,
        "best_optimized_throughput.latency_ms": 0.879383996129036,
        "best_optimized_throughput.requests_per_s": 4548.6386124919445,
        "best_optimized_throughput.tokens_per_s": 298099580.1082721,
        "best_optimized_time_ms": 0.879383996129036,
        "best_speedup": 1.0
      },
      "type": "python"
    },
    "prefill_decode_disagg": {
      "example": "prefill_decode_disagg",
      "metadata": {
        "best_optimization": "optimized_prefill_decode_disagg",
        "best_optimization_file": "optimized_prefill_decode_disagg.py",
        "best_optimization_speedup": 3.8312319860365163,
        "best_optimization_time_ms": 1.4974688172340394,
        "git_commit": "31bb5bdcfabc2dd956bb8ce8988785b9f6559ed8",
        "updated_at": "2025-11-25T02:46:14.774956"
      },
      "metrics": {
        "baseline_p75_ms": 5.694047927856445,
        "baseline_throughput.latency_ms": 5.737150430679321,
        "baseline_throughput.requests_per_s": 174.30255874981347,
        "baseline_throughput.tokens_per_s": 47410.29597994926,
        "baseline_time_ms": 5.737150430679321,
        "best_optimized_p75_ms": 1.4355520009994507,
        "best_optimized_speedup": 3.8312319860365163,
        "best_optimized_throughput.latency_ms": 1.4974688172340394,
        "best_optimized_throughput.requests_per_s": 2671.1741533211775,
        "best_optimized_throughput.tokens_per_s": 6154385.249251992,
        "best_optimized_time_ms": 1.4974688172340394,
        "best_speedup": 3.8312319860365163
      },
      "type": "python"
    },
    "routing_static": {
      "example": "routing_static",
      "metadata": {
        "best_optimization": "optimized_routing_static",
        "best_optimization_file": "optimized_routing_static.py",
        "best_optimization_speedup": 1.69574673123186,
        "best_optimization_time_ms": 3.5301811265945435,
        "git_commit": "31bb5bdcfabc2dd956bb8ce8988785b9f6559ed8",
        "updated_at": "2025-11-25T02:46:14.774967"
      },
      "metrics": {
        "baseline_p75_ms": 5.980703830718994,
        "baseline_throughput.latency_ms": 5.986293106079102,
        "baseline_throughput.requests_per_s": 1670.4828552155197,
        "baseline_throughput.tokens_per_s": 54738382.19970215,
        "baseline_time_ms": 5.986293106079102,
        "best_optimized_p75_ms": 3.476032018661499,
        "best_optimized_speedup": 1.69574673123186,
        "best_optimized_throughput.latency_ms": 3.5301811265945435,
        "best_optimized_throughput.requests_per_s": 2832.7158413105817,
        "best_optimized_throughput.tokens_per_s": 92822432.68806514,
        "best_optimized_time_ms": 3.5301811265945435,
        "best_speedup": 1.69574673123186
      },
      "type": "python"
    }
  },
  "hardware_key": "b200"
}
