{
  "examples": {
    "continuous_batching": {
      "example": "continuous_batching",
      "metadata": {
        "best_optimization": "optimized_continuous_batching",
        "best_optimization_file": "optimized_continuous_batching.py",
        "best_optimization_speedup": 25.520327368064333,
        "best_optimization_time_ms": 0.027312000375241043,
        "git_commit": "31bb5bdcfabc2dd956bb8ce8988785b9f6559ed8",
        "updated_at": "2025-11-25T04:34:46.033356"
      },
      "metrics": {
        "baseline_p75_ms": 0.6502400040626526,
        "baseline_throughput.latency_ms": 0.7246623933315277,
        "baseline_throughput.requests_per_s": 16559.4352769319,
        "baseline_throughput.tokens_per_s": 203482340.6829392,
        "baseline_time_ms": 0.7246623933315277,
        "best_optimized_p75_ms": 0.01958400011062622,
        "best_optimized_speedup": 25.520327368064333,
        "best_optimized_throughput.latency_ms": 0.027312000375241043,
        "best_optimized_throughput.requests_per_s": 5858230.733807535,
        "best_optimized_throughput.tokens_per_s": 5998828271.418916,
        "best_optimized_time_ms": 0.027312000375241043,
        "best_speedup": 25.520327368064333
      },
      "type": "python"
    },
    "disaggregated_inference": {
      "example": "disaggregated_inference",
      "metadata": {
        "best_optimization": "optimized_disaggregated_inference",
        "best_optimization_file": "optimized_disaggregated_inference.py",
        "best_optimization_speedup": 0.97019190964286,
        "best_optimization_time_ms": 440.4897232055664,
        "git_commit": "93e7c34588cfab78bdfc5128a3b7c3f3e4254747",
        "updated_at": "2025-11-25T11:33:13.928404"
      },
      "metrics": {
        "baseline_p75_ms": 561.371337890625,
        "baseline_throughput.latency_ms": 427.3595657348633,
        "baseline_throughput.requests_per_s": 4.679899925864333,
        "baseline_throughput.tokens_per_s": 9883.94864342547,
        "baseline_time_ms": 427.3595657348633,
        "best_optimized_p75_ms": 413.553466796875,
        "best_optimized_speedup": 0.97019190964286,
        "best_optimized_throughput.latency_ms": 415.8374328613281,
        "best_optimized_throughput.requests_per_s": 4.8095718229074205,
        "best_optimized_throughput.tokens_per_s": 10157.815689980473,
        "best_optimized_time_ms": 415.8374328613281,
        "best_speedup": 1.0
      },
      "type": "python"
    },
    "expert_parallelism": {
      "example": "expert_parallelism",
      "metadata": {
        "best_optimization": "optimized_expert_parallelism",
        "best_optimization_file": "optimized_expert_parallelism.py",
        "best_optimization_speedup": 0.745953090114154,
        "best_optimization_time_ms": 1.3047984033823012,
        "git_commit": "31bb5bdcfabc2dd956bb8ce8988785b9f6559ed8",
        "updated_at": "2025-11-25T04:35:09.781258"
      },
      "metrics": {
        "baseline_p75_ms": 0.9466879963874817,
        "baseline_throughput.latency_ms": 0.9733184009790421,
        "baseline_throughput.requests_per_s": 1027.4130222896426,
        "baseline_throughput.tokens_per_s": 1052070.934824594,
        "baseline_time_ms": 0.9733184009790421,
        "best_optimized_p75_ms": 1.6163519620895386,
        "best_optimized_speedup": 0.7655172737157676,
        "best_optimized_throughput.latency_ms": 1.351939195394516,
        "best_optimized_throughput.requests_per_s": 739.6782365705325,
        "best_optimized_throughput.tokens_per_s": 757430.5142482253,
        "best_optimized_time_ms": 1.351939195394516,
        "best_speedup": 1.0
      },
      "type": "python"
    },
    "inference_monolithic": {
      "example": "inference_monolithic",
      "metadata": {
        "best_optimization": "optimized_inference_monolithic",
        "best_optimization_file": "optimized_inference_monolithic.py",
        "best_optimization_speedup": 1.1911756265635423,
        "best_optimization_time_ms": 4.955000019073486,
        "git_commit": "31bb5bdcfabc2dd956bb8ce8988785b9f6559ed8",
        "updated_at": "2025-11-25T02:46:14.760757"
      },
      "metrics": {
        "baseline_p75_ms": 5.9232001304626465,
        "baseline_throughput.latency_ms": 5.902275252342224,
        "baseline_throughput.requests_per_s": 169.4261885877257,
        "baseline_throughput.tokens_per_s": 46083.923295861394,
        "baseline_time_ms": 5.902275252342224,
        "best_optimized_p75_ms": 4.930208206176758,
        "best_optimized_speedup": 1.1911756265635423,
        "best_optimized_throughput.latency_ms": 4.955000019073486,
        "best_optimized_throughput.requests_per_s": 201.81634634725705,
        "best_optimized_throughput.tokens_per_s": 3229.061541556113,
        "best_optimized_time_ms": 4.955000019073486,
        "best_speedup": 1.1911756265635423
      },
      "type": "python"
    },
    "inference_placement": {
      "example": "inference_placement",
      "metadata": {
        "best_optimization": "optimized_inference_placement",
        "best_optimization_file": "optimized_inference_placement.py",
        "best_optimization_speedup": 1.05,
        "best_optimization_time_ms": 2.6891520023345947,
        "git_commit": "31bb5bdcfabc2dd956bb8ce8988785b9f6559ed8",
        "updated_at": "2025-11-25T02:46:14.760766"
      },
      "metrics": {
        "baseline_p75_ms": 2.1161599159240723,
        "baseline_throughput.latency_ms": 2.1161599159240723,
        "baseline_throughput.requests_per_s": 472.55407895925765,
        "baseline_time_ms": 2.1161599159240723,
        "best_optimized_p75_ms": 2.6891520023345947,
        "best_optimized_speedup": 0.7869246193918835,
        "best_optimized_throughput.latency_ms": 2.6891520023345947,
        "best_optimized_throughput.requests_per_s": 371.8644387270959,
        "best_optimized_time_ms": 2.6891520023345947,
        "best_speedup": 1.0
      },
      "type": "python"
    },
    "kv_cache_management": {
      "example": "kv_cache_management",
      "metadata": {
        "best_optimization": "optimized_kv_cache_management",
        "best_optimization_file": "optimized_kv_cache_management.py",
        "best_optimization_speedup": 23.43372447955259,
        "best_optimization_time_ms": 0.3466016039252281,
        "git_commit": "2e62787eff329e2d792c1e48583eace9d4ddad8e",
        "updated_at": "2025-11-30T04:59:55.253379"
      },
      "metrics": {
        "baseline_p75_ms": 9.593024253845215,
        "baseline_throughput.latency_ms": 9.324201583862305,
        "baseline_throughput.requests_per_s": 1141.346133116771,
        "baseline_throughput.tokens_per_s": 36523.07625973667,
        "baseline_time_ms": 9.324201583862305,
        "best_optimized_p75_ms": 0.28195199370384216,
        "best_optimized_speedup": 23.43372447955259,
        "best_optimized_throughput.latency_ms": 0.3466016039252281,
        "best_optimized_throughput.requests_per_s": 23081.25498959269,
        "best_optimized_throughput.tokens_per_s": 738600.1596669661,
        "best_optimized_time_ms": 0.3466016039252281,
        "best_speedup": 23.43372447955259
      },
      "type": "python"
    },
    "kv_cache_management_math": {
      "example": "kv_cache_management_math",
      "metadata": {
        "best_optimization": "optimized_kv_cache_management_math",
        "best_optimization_file": "optimized_kv_cache_management_math.py",
        "best_optimization_speedup": 8.793394761212527,
        "best_optimization_time_ms": 0.8412576079368591,
        "git_commit": "2e62787eff329e2d792c1e48583eace9d4ddad8e",
        "updated_at": "2025-11-29T18:32:13.312936"
      },
      "metrics": {
        "baseline_p75_ms": 7.342239856719971,
        "baseline_throughput.latency_ms": 7.397510242462158,
        "baseline_throughput.requests_per_s": 1081.444937254634,
        "baseline_throughput.tokens_per_s": 34606.237992148286,
        "baseline_time_ms": 7.397510242462158,
        "best_optimized_p75_ms": 0.9812160134315491,
        "best_optimized_speedup": 8.793394761212527,
        "best_optimized_throughput.latency_ms": 1.0017375946044922,
        "best_optimized_throughput.requests_per_s": 7986.123355147288,
        "best_optimized_throughput.tokens_per_s": 383333.92104706983,
        "best_optimized_time_ms": 1.0017375946044922,
        "best_speedup": 8.793394761212527
      },
      "type": "python"
    },
    "moe_inference": {
      "example": "moe_inference",
      "metadata": {
        "best_optimization": "optimized_moe_inference",
        "best_optimization_file": "optimized_moe_inference.py",
        "best_optimization_speedup": 1.4326212460032972,
        "best_optimization_time_ms": 450.0745493570964,
        "git_commit": "2e62787eff329e2d792c1e48583eace9d4ddad8e",
        "updated_at": "2025-11-29T18:32:30.325933"
      },
      "metrics": {
        "baseline_p75_ms": 661.4796752929688,
        "baseline_throughput.latency_ms": 767.283561706543,
        "baseline_throughput.requests_per_s": 2.6065982640781824,
        "baseline_throughput.tokens_per_s": 5505.1355337331215,
        "baseline_time_ms": 767.283561706543,
        "best_optimized_p75_ms": 508.3792724609375,
        "best_optimized_speedup": 1.9060433017782206,
        "best_optimized_throughput.latency_ms": 499.1707356770833,
        "best_optimized_throughput.requests_per_s": 2.00332256786565,
        "best_optimized_throughput.tokens_per_s": 1089.8074769189134,
        "best_optimized_time_ms": 499.1707356770833,
        "best_speedup": 1.9060433017782206
      },
      "type": "python"
    },
    "moe_validation": {
      "example": "moe_validation",
      "metadata": {
        "best_optimization": "optimized_moe_validation",
        "best_optimization_file": "optimized_moe_validation.py",
        "best_optimization_speedup": 0.0361856601299041,
        "best_optimization_time_ms": 2020.934326171875,
        "git_commit": "31bb5bdcfabc2dd956bb8ce8988785b9f6559ed8",
        "updated_at": "2025-11-25T04:36:19.689583"
      },
      "metrics": {
        "baseline_p75_ms": 69.72582244873047,
        "baseline_throughput.latency_ms": 75.6201171875,
        "baseline_throughput.requests_per_s": 26.447988635629883,
        "baseline_throughput.tokens_per_s": 13964.537999612578,
        "baseline_time_ms": 75.6201171875,
        "best_optimized_p75_ms": 2075.642333984375,
        "best_optimized_speedup": 0.0361856601299041,
        "best_optimized_throughput.latency_ms": 2075.642333984375,
        "best_optimized_throughput.requests_per_s": 0.9635571443374962,
        "best_optimized_throughput.tokens_per_s": 508.758172210198,
        "best_optimized_time_ms": 2075.642333984375,
        "best_speedup": 1.0
      },
      "type": "python"
    }
  },
  "hardware_key": "b200"
}
